fizzy.py
fizzy-1.0.0.dist-info/LICENSE
fizzy-1.0.0.dist-info/METADATA
fizzy-1.0.0.dist-info/WHEEL
fizzy-1.0.0.dist-info/entry_points.txt
fizzy-1.0.0.dist-info/top_level.txt
fizzy-1.0.0.dist-info/RECORD
